LICENSE
MANIFEST.in
README.md
setup.py
fifo/__init__.py
fifo/worker.py
fifo.egg-info/PKG-INFO
fifo.egg-info/SOURCES.txt
fifo.egg-info/dependency_links.txt
fifo.egg-info/requires.txt
fifo.egg-info/top_level.txt