Metadata-Version: 1.1
Name: fifo
Version: 0.0.3
Summary: A simple redis based task queue for python
Home-page: http://github.com/fergalwalsh/fifo
Author: Fergal Walsh
Author-email: fergalwalsh@gmail.com
License: BSD License
Download-URL: https://github.com/fergalwalsh/fifo/tarball/0.0.3
Platform: UNKNOWN
